<?xml version="1.0" encoding="utf-8"?>
<!DOCTYPE hibernate-mapping PUBLIC "-//Hibernate/Hibernate Mapping DTD 3.0//EN"
"http://hibernate.sourceforge.net/hibernate-mapping-3.0.dtd">
<!-- 
    Mapping file autogenerated by MyEclipse Persistence Tools
-->
<hibernate-mapping>
    <class name="com.moment.beans.momentRecommend.UserPreference" table="user_preference">
        <id name="id" column="id" type="java.lang.Integer">   
        <generator class="native" />  
        </id> 
        <property name="userId" column="user_id" type="java.lang.Integer"></property>
        <property name="classifyId" column="classifyId" type="java.lang.Integer"></property> 
        <property name="preferenceMark" column="preference_mark" type="java.lang.Integer"></property>              
    </class>
</hibernate-mapping>